doccmd/__init__.py
doccmd/__main__.py
doccmd/_setuptools_scm_version.py
doccmd/py.typed
doccmd-2026.1.31.3.dist-info/licenses/LICENSE
doccmd-2026.1.31.3.dist-info/METADATA
doccmd-2026.1.31.3.dist-info/WHEEL
doccmd-2026.1.31.3.dist-info/entry_points.txt
doccmd-2026.1.31.3.dist-info/top_level.txt
doccmd-2026.1.31.3.dist-info/RECORD
