Metadata-Version: 2.4
Name: doccmd
Version: 2026.1.31.3
Summary: Run commands against code blocks in reStructuredText and Markdown files.
Author-email: Adam Dangoor <adamdangoor@gmail.com>
License-Expression: MIT
Project-URL: Documentation, https://adamtheturtle.github.io/doccmd/
Project-URL: Source, https://github.com/adamtheturtle/doccmd
Keywords: markdown,rst,sphinx,testing
Classifier: Development Status :: 5 - Production/Stable
Classifier: Environment :: Web Environment
Classifier: Operating System :: Microsoft :: Windows
Classifier: Operating System :: POSIX
Classifier: Programming Language :: Python :: 3 :: Only
Classifier: Programming Language :: Python :: 3.10
Classifier: Programming Language :: Python :: 3.11
Classifier: Programming Language :: Python :: 3.12
Classifier: Programming Language :: Python :: 3.13
Classifier: Programming Language :: Python :: 3.14
Requires-Python: >=3.10
License-File: LICENSE
Requires-Dist: beartype>=0.22.9
Requires-Dist: charset-normalizer>=3.4.1
Requires-Dist: click<8.4.0,>=8.3.0
Requires-Dist: click-compose>=2025.10.27.3
Requires-Dist: cloup>=3.0.0
Requires-Dist: dulwich>=0.22.1
Requires-Dist: pygments>=2.18.0
Requires-Dist: sybil<10.0.0,>=9.3.0
Requires-Dist: sybil-extras==2026.1.27
Provides-Extra: dev
Requires-Dist: actionlint-py==1.7.10.24; extra == "dev"
Requires-Dist: ansi==0.3.7; extra == "dev"
Requires-Dist: check-manifest==0.51; extra == "dev"
Requires-Dist: deptry==0.24.0; extra == "dev"
Requires-Dist: doc8==2.0.0; extra == "dev"
Requires-Dist: furo==2025.12.19; extra == "dev"
Requires-Dist: hadolint-bin==2.14.0; sys_platform != "win32" and extra == "dev"
Requires-Dist: interrogate==1.7.0; extra == "dev"
Requires-Dist: mypy[faster-cache]==1.19.1; extra == "dev"
Requires-Dist: mypy-strict-kwargs==2026.1.12; extra == "dev"
Requires-Dist: prek==0.3.0; extra == "dev"
Requires-Dist: pydocstringformatter==0.7.5; extra == "dev"
Requires-Dist: pydocstyle==6.3; extra == "dev"
Requires-Dist: pygments==2.19.2; extra == "dev"
Requires-Dist: pylint[spelling]==4.0.4; extra == "dev"
Requires-Dist: pylint-per-file-ignores==3.2.0; extra == "dev"
Requires-Dist: pyproject-fmt==2.11.1; extra == "dev"
Requires-Dist: pyrefly==0.50.1; extra == "dev"
Requires-Dist: pyright==1.1.408; extra == "dev"
Requires-Dist: pyroma==5.0.1; extra == "dev"
Requires-Dist: pytest==9.0.2; extra == "dev"
Requires-Dist: pytest-cov==7.0.0; extra == "dev"
Requires-Dist: pytest-regressions==2.9.1; extra == "dev"
Requires-Dist: pyyaml==6.0.3; extra == "dev"
Requires-Dist: ruff==0.14.14; extra == "dev"
Requires-Dist: shellcheck-py==0.11.0.1; extra == "dev"
Requires-Dist: shfmt-py==3.12.0.2; extra == "dev"
Requires-Dist: sphinx>=8.1.3; extra == "dev"
Requires-Dist: sphinx-click==6.2.0; extra == "dev"
Requires-Dist: sphinx-copybutton==0.5.2; extra == "dev"
Requires-Dist: sphinx-inline-tabs==2025.12.21.14; extra == "dev"
Requires-Dist: sphinx-lint==1.0.2; extra == "dev"
Requires-Dist: sphinx-pyproject==0.3.0; extra == "dev"
Requires-Dist: sphinx-substitution-extensions==2026.1.12; extra == "dev"
Requires-Dist: sphinxcontrib-spelling==8.0.2; extra == "dev"
Requires-Dist: ty==0.0.14; extra == "dev"
Requires-Dist: types-pygments==2.19.0.20251121; extra == "dev"
Requires-Dist: vulture==2.14; extra == "dev"
Requires-Dist: yamlfix==1.19.1; extra == "dev"
Requires-Dist: zizmor==1.22.0; extra == "dev"
Provides-Extra: release
Requires-Dist: check-wheel-contents==0.6.3; extra == "release"
Requires-Dist: homebrew-pypi-poet==0.10; extra == "release"
Dynamic: license-file
